audiomatch-0.2.2.dist-info/WHEEL
audiomatch-0.2.2.dist-info/METADATA
audiomatch-0.2.2.dist-info/entry_points.txt
audiomatch-0.2.2.dist-info/RECORD
audiomatch-0.2.2.dist-info/LICENSE
audiomatch/match.py
audiomatch/cli.py
audiomatch/reports.py
audiomatch/py.typed
audiomatch/fingerprints.py
audiomatch/__main__.py
audiomatch/files.py
audiomatch/exceptions.py
audiomatch/constants.py
audiomatch/__init__.py
audiomatch/popcount/_popcount.cpython-38-x86_64-linux-gnu.so
audiomatch/popcount/_popcount.c
audiomatch/popcount/_popcount.pyx
audiomatch/popcount/_popcount.pyi
audiomatch/popcount/__init__.py
