Metadata-Version: 2.1
Name: audiomatch
Version: 0.2.2
Summary: A small command-line tool to find similar audio files
License: MIT
Keywords: duplicate,detection,audio,fingerprinting,command-line
Author: Aleksei Maslakov
Author-email: lesha.maslakov@gmail.com
Requires-Python: >=3.8,<4.0
Classifier: Development Status :: 4 - Beta
Classifier: License :: OSI Approved :: MIT License
Classifier: Operating System :: OS Independent
Classifier: Programming Language :: Python :: 3
Classifier: Programming Language :: Python :: 3.8
Classifier: Topic :: Multimedia :: Sound/Audio :: Analysis
Classifier: Typing :: Typed
